file_updater-0.0.8.data/scripts/lofup.py
fup/__init__.py
fup/progress_bar.py
fup/updater.py
file_updater-0.0.8.dist-info/METADATA
file_updater-0.0.8.dist-info/WHEEL
file_updater-0.0.8.dist-info/top_level.txt
file_updater-0.0.8.dist-info/RECORD
