Metadata-Version: 2.1
Name: file-updater
Version: 0.0.8
Summary: Local file updater
Home-page: UNKNOWN
Author: Daniel Riffert
Author-email: riffert.daniel@gmail.com
License: UNKNOWN
Keywords: file,update,path,backup
Platform: windows
Requires-Dist: colorama
Requires-Dist: pywin32
